mobi_header/__init__.py
mobi_header/mobi_header.py
mobi_header-0.0.4.dist-info/LICENSE
mobi_header-0.0.4.dist-info/METADATA
mobi_header-0.0.4.dist-info/WHEEL
mobi_header-0.0.4.dist-info/top_level.txt
mobi_header-0.0.4.dist-info/RECORD
