Metadata-Version: 2.1
Name: mobi_header
Version: 0.0.4
Summary: A python library for reading/editing mobi/azw3 metadata.
Author-email: Sola <sola1211582552@outlook.com>
Project-URL: Homepage, https://github.com/SolaProject/mobi_header
Project-URL: Bug Tracker, https://github.com/SolaProject/mobi_header/issues
Classifier: Programming Language :: Python :: 3
Classifier: License :: OSI Approved :: GNU General Public License v3 (GPLv3)
Classifier: Operating System :: OS Independent
Requires-Python: >=3.7
License-File: LICENSE
Requires-Dist: requests
